MidoWebLib/__init__.py
MidoWebLib/apis_url.py
MidoWebLib/gaps.py
MidoWebLib/servergaps.py
MidoWebLib/setup.py
midoweblib-0.2.dist-info/LICENSE.txt
midoweblib-0.2.dist-info/METADATA
midoweblib-0.2.dist-info/WHEEL
midoweblib-0.2.dist-info/top_level.txt
midoweblib-0.2.dist-info/RECORD
