Metadata-Version: 2.2
Name: MidoWebLib
Version: 0.2
Summary: A library for Mido Web Website
Home-page: https://midoghanam2.pythonanywhere.com/
Author: Mohammed Ahmed Ghanam
Author-email: mghanam883@outlook.com
License: MIT
Classifier: Programming Language :: Python :: 3
Classifier: License :: OSI Approved :: MIT License
Classifier: Operating System :: OS Independent
Requires-Python: >=3.6
License-File: LICENSE.txt
Requires-Dist: requests
Dynamic: author
Dynamic: author-email
Dynamic: classifier
Dynamic: description
Dynamic: description-content-type
Dynamic: home-page
Dynamic: license
Dynamic: requires-dist
Dynamic: requires-python
Dynamic: summary
